LICENSE
MANIFEST.in
README.md
requirements.txt
setup.cfg
setup.py
hipchat_notif/__init__.py
hipchat_notif/error.py
hipchat_notif/hipchat_notif.py
hipchat_notif.egg-info/PKG-INFO
hipchat_notif.egg-info/SOURCES.txt
hipchat_notif.egg-info/dependency_links.txt
hipchat_notif.egg-info/requires.txt
hipchat_notif.egg-info/top_level.txt