Metadata-Version: 1.1
Name: hipchat-notif
Version: 0.2.3
Summary: Simple Python library for the HipChat API v1
Home-page: https://bitbucket.org/rodevl/hipchat_notif
Author: Denis Rogov
Author-email: rogovdv@gmail.com
License: MIT
Download-URL: https://bitbucket.org/rodevl/hipchat_notif/get/0.2.3.zip
Keywords: HipChat,HipChat Client
Platform: UNKNOWN
Classifier: License :: OSI Approved :: MIT License
Classifier: Programming Language :: Python :: 3.4
Classifier: Programming Language :: Python :: 2.7
Classifier: Topic :: Communications :: Chat
